odoo10_addon_sale_sourced_by_line-10.0.1.0.0-py2.7-nspkg.pth
odoo/addons/sale_sourced_by_line/README.rst
odoo/addons/sale_sourced_by_line/__init__.py
odoo/addons/sale_sourced_by_line/__manifest__.py
odoo/addons/sale_sourced_by_line/i18n/ca.po
odoo/addons/sale_sourced_by_line/i18n/de.po
odoo/addons/sale_sourced_by_line/i18n/el_GR.po
odoo/addons/sale_sourced_by_line/i18n/es.po
odoo/addons/sale_sourced_by_line/i18n/es_ES.po
odoo/addons/sale_sourced_by_line/i18n/es_VE.po
odoo/addons/sale_sourced_by_line/i18n/fi.po
odoo/addons/sale_sourced_by_line/i18n/fr.po
odoo/addons/sale_sourced_by_line/i18n/hr.po
odoo/addons/sale_sourced_by_line/i18n/hr_HR.po
odoo/addons/sale_sourced_by_line/i18n/hu.po
odoo/addons/sale_sourced_by_line/i18n/it.po
odoo/addons/sale_sourced_by_line/i18n/nl.po
odoo/addons/sale_sourced_by_line/i18n/pt.po
odoo/addons/sale_sourced_by_line/i18n/pt_BR.po
odoo/addons/sale_sourced_by_line/i18n/ro.po
odoo/addons/sale_sourced_by_line/i18n/sale_sourced_by_line.pot
odoo/addons/sale_sourced_by_line/i18n/sl.po
odoo/addons/sale_sourced_by_line/i18n/tr.po
odoo/addons/sale_sourced_by_line/i18n/tr_TR.po
odoo/addons/sale_sourced_by_line/i18n/vi_VN.po
odoo/addons/sale_sourced_by_line/i18n/zh_CN.po
odoo/addons/sale_sourced_by_line/model/__init__.py
odoo/addons/sale_sourced_by_line/model/sale.py
odoo/addons/sale_sourced_by_line/static/description/icon.png
odoo/addons/sale_sourced_by_line/test/sale_order_multi_source.yml
odoo/addons/sale_sourced_by_line/test/sale_order_not_sourced.yml
odoo/addons/sale_sourced_by_line/test/sale_order_source.yml
odoo/addons/sale_sourced_by_line/tests/__init__.py
odoo/addons/sale_sourced_by_line/tests/test_sale_is_delivered.py
odoo/addons/sale_sourced_by_line/tests/test_sale_sourced_by_line.py
odoo/addons/sale_sourced_by_line/view/sale_view.xml
odoo10_addon_sale_sourced_by_line-10.0.1.0.0.dist-info/DESCRIPTION.rst
odoo10_addon_sale_sourced_by_line-10.0.1.0.0.dist-info/METADATA
odoo10_addon_sale_sourced_by_line-10.0.1.0.0.dist-info/RECORD
odoo10_addon_sale_sourced_by_line-10.0.1.0.0.dist-info/WHEEL
odoo10_addon_sale_sourced_by_line-10.0.1.0.0.dist-info/metadata.json
odoo10_addon_sale_sourced_by_line-10.0.1.0.0.dist-info/namespace_packages.txt
odoo10_addon_sale_sourced_by_line-10.0.1.0.0.dist-info/top_level.txt
